bird_telerik/__init__.py
bird_telerik/ui/Telerik.WinControls.Themes.Office2013Dark.dll
bird_telerik/ui/Telerik.WinControls.Themes.Office2013Light.dll
bird_telerik/ui/Telerik.WinControls.Themes.VisualStudio2012Dark.dll
bird_telerik/ui/Telerik.WinControls.Themes.VisualStudio2012Light.dll
bird_telerik/ui/Telerik.WinControls.Themes.Windows11.dll
bird_telerik/ui/Telerik.WinControls.UI.dll
bird_telerik/ui/Telerik.WinControls.dll
bird_telerik/ui/__init__.py
bird_telerik/ui/button.py
bird_telerik/ui/taskbarbutton.py
bird_telerik/ui/thumbnailbutton.py
bird_telerik/ui/widget.py
bird_telerik/ui/window.py
bird_telerik/ui/themes/__init__.py
bird_dev_form_telerik-1.0.0a1.dist-info/METADATA
bird_dev_form_telerik-1.0.0a1.dist-info/WHEEL
bird_dev_form_telerik-1.0.0a1.dist-info/top_level.txt
bird_dev_form_telerik-1.0.0a1.dist-info/RECORD
